Classfile /home/aman/Desktop/experiments/reproducible-central/results/com.google.guava/guava/32.0.1-jre/guava-32.0.1-jre.jar/jNorm/rebuild/LocalCache$EntryIterator.class
  Last modified Oct 22, 2024; size 1328 bytes
  SHA-256 checksum 3ebc0f3c1f1d0e750454202080db0c00c00075261ad0214f9eeb2ccf872038b3
  Compiled from "LocalCache.java"
final class com.google.common.cache.LocalCache$EntryIterator extends com.google.common.cache.LocalCache<K, V>.HashIterator<java.util.Map$Entry<K, V>>
  minor version: 0
  major version: 52
  flags: (0x0030) ACC_FINAL, ACC_SUPER
  this_class: #5                          // com/google/common/cache/LocalCache$EntryIterator
  super_class: #6                         // com/google/common/cache/LocalCache$HashIterator
  interfaces: 0, fields: 1, methods: 3, attributes: 3
Constant pool:
   #1 = Fieldref           #5.#32         // com/google/common/cache/LocalCache$EntryIterator.this$0:Lcom/google/common/cache/LocalCache;
   #2 = Methodref          #6.#33         // com/google/common/cache/LocalCache$HashIterator."<init>":(Lcom/google/common/cache/LocalCache;)V
   #3 = Methodref          #5.#34         // com/google/common/cache/LocalCache$EntryIterator.nextEntry:()Lcom/google/common/cache/LocalCache$WriteThroughEntry;
   #4 = Methodref          #5.#35         // com/google/common/cache/LocalCache$EntryIterator.next:()Ljava/util/Map$Entry;
   #5 = Class              #37            // com/google/common/cache/LocalCache$EntryIterator
   #6 = Class              #38            // com/google/common/cache/LocalCache$HashIterator
   #7 = Utf8               this$0
   #8 = Utf8               Lcom/google/common/cache/LocalCache;
   #9 = Utf8               <init>
  #10 = Utf8               (Lcom/google/common/cache/LocalCache;)V
  #11 = Utf8               Code
  #12 = Utf8               LineNumberTable
  #13 = Utf8               LocalVariableTable
  #14 = Utf8               this
  #15 = Utf8               EntryIterator
  #16 = Utf8               InnerClasses
  #17 = Utf8               Lcom/google/common/cache/LocalCache$EntryIterator;
  #18 = Utf8               LocalVariableTypeTable
  #19 = Utf8               Lcom/google/common/cache/LocalCache<TK;TV;>.EntryIterator;
  #20 = Utf8               MethodParameters
  #21 = Utf8               next
  #22 = Class              #40            // java/util/Map$Entry
  #23 = Utf8               Entry
  #24 = Utf8               ()Ljava/util/Map$Entry;
  #25 = Utf8               Signature
  #26 = Utf8               ()Ljava/util/Map$Entry<TK;TV;>;
  #27 = Utf8               ()Ljava/lang/Object;
  #28 = Utf8               HashIterator
  #29 = Utf8               Lcom/google/common/cache/LocalCache<TK;TV;>.HashIterator<Ljava/util/Map$Entry<TK;TV;>;>;
  #30 = Utf8               SourceFile
  #31 = Utf8               LocalCache.java
  #32 = NameAndType        #7:#8          // this$0:Lcom/google/common/cache/LocalCache;
  #33 = NameAndType        #9:#10         // "<init>":(Lcom/google/common/cache/LocalCache;)V
  #34 = NameAndType        #41:#44        // nextEntry:()Lcom/google/common/cache/LocalCache$WriteThroughEntry;
  #35 = NameAndType        #21:#24        // next:()Ljava/util/Map$Entry;
  #36 = Class              #45            // com/google/common/cache/LocalCache
  #37 = Utf8               com/google/common/cache/LocalCache$EntryIterator
  #38 = Utf8               com/google/common/cache/LocalCache$HashIterator
  #39 = Class              #46            // java/util/Map
  #40 = Utf8               java/util/Map$Entry
  #41 = Utf8               nextEntry
  #42 = Class              #47            // com/google/common/cache/LocalCache$WriteThroughEntry
  #43 = Utf8               WriteThroughEntry
  #44 = Utf8               ()Lcom/google/common/cache/LocalCache$WriteThroughEntry;
  #45 = Utf8               com/google/common/cache/LocalCache
  #46 = Utf8               java/util/Map
  #47 = Utf8               com/google/common/cache/LocalCache$WriteThroughEntry
{
  final com.google.common.cache.LocalCache this$0;
    descriptor: Lcom/google/common/cache/LocalCache;
    flags: (0x1010) ACC_FINAL, ACC_SYNTHETIC

  com.google.common.cache.LocalCache$EntryIterator(com.google.common.cache.LocalCache);
    descriptor: (Lcom/google/common/cache/LocalCache;)V
    flags: (0x0000)
    Code:
      stack=2, locals=2, args_size=2
         0: aload_0
         1: aload_1
         2: putfield      #1                  // Field this$0:Lcom/google/common/cache/LocalCache;
         5: aload_0
         6: aload_1
         7: invokespecial #2                  // Method com/google/common/cache/LocalCache$HashIterator."<init>":(Lcom/google/common/cache/LocalCache;)V
        10: return
      LineNumberTable:
        line 4558: 0
      LocalVariableTable:
        Start  Length  Slot  Name   Signature
            0      11     0  this   Lcom/google/common/cache/LocalCache$EntryIterator;
            0      11     1 this$0   Lcom/google/common/cache/LocalCache;
      LocalVariableTypeTable:
        Start  Length  Slot  Name   Signature
            0      11     0  this   Lcom/google/common/cache/LocalCache<TK;TV;>.EntryIterator;
    MethodParameters:
      Name                           Flags
      this$0                         final mandated

  public java.util.Map$Entry<K, V> next();
    descriptor: ()Ljava/util/Map$Entry;
    flags: (0x0001) ACC_PUBLIC
    Code:
      stack=1, locals=1, args_size=1
         0: aload_0
         1: invokevirtual #3                  // Method nextEntry:()Lcom/google/common/cache/LocalCache$WriteThroughEntry;
         4: areturn
      LineNumberTable:
        line 4562: 0
      LocalVariableTable:
        Start  Length  Slot  Name   Signature
            0       5     0  this   Lcom/google/common/cache/LocalCache$EntryIterator;
      LocalVariableTypeTable:
        Start  Length  Slot  Name   Signature
            0       5     0  this   Lcom/google/common/cache/LocalCache<TK;TV;>.EntryIterator;
    Signature: #26                          // ()Ljava/util/Map$Entry<TK;TV;>;

  public java.lang.Object next();
    descriptor: ()Ljava/lang/Object;
    flags: (0x1041) ACC_PUBLIC, ACC_BRIDGE, ACC_SYNTHETIC
    Code:
      stack=1, locals=1, args_size=1
         0: aload_0
         1: invokevirtual #4                  // Method next:()Ljava/util/Map$Entry;
         4: areturn
      LineNumberTable:
        line 4558: 0
      LocalVariableTable:
        Start  Length  Slot  Name   Signature
            0       5     0  this   Lcom/google/common/cache/LocalCache$EntryIterator;
      LocalVariableTypeTable:
        Start  Length  Slot  Name   Signature
            0       5     0  this   Lcom/google/common/cache/LocalCache<TK;TV;>.EntryIterator;
}
Signature: #29                          // Lcom/google/common/cache/LocalCache<TK;TV;>.HashIterator<Ljava/util/Map$Entry<TK;TV;>;>;
SourceFile: "LocalCache.java"
InnerClasses:
  final #15= #5 of #36;                   // EntryIterator=class com/google/common/cache/LocalCache$EntryIterator of class com/google/common/cache/LocalCache
  public static #23= #22 of #39;          // Entry=class java/util/Map$Entry of class java/util/Map
  abstract #28= #6 of #36;                // HashIterator=class com/google/common/cache/LocalCache$HashIterator of class com/google/common/cache/LocalCache
  final #43= #42 of #36;                  // WriteThroughEntry=class com/google/common/cache/LocalCache$WriteThroughEntry of class com/google/common/cache/LocalCache
